lcdbackpack/__init__.py
lcdbackpack/lcdbackpack.py
lcdbackpack-1.0.0b1.dist-info/DESCRIPTION.rst
lcdbackpack-1.0.0b1.dist-info/METADATA
lcdbackpack-1.0.0b1.dist-info/RECORD
lcdbackpack-1.0.0b1.dist-info/WHEEL
lcdbackpack-1.0.0b1.dist-info/metadata.json
lcdbackpack-1.0.0b1.dist-info/top_level.txt
