Metadata-Version: 2.0
Name: lcdbackpack
Version: 1.0.0b1
Summary: A wrapper library to facilitate writing text and commands to the Adafruit USB / Serial LCD Backpack
Home-page: https://github.com/dinofizz/adafruit-usb-serial-lcd-backpack
Author: Dino Fizzotti
Author-email: dino@dinofizzotti.com
License: BSD
Keywords: USB serial port LCD Adafruit
Platform: UNKNOWN
Classifier: Development Status :: 4 - Beta
Classifier: Intended Audience :: Developers
Classifier: Topic :: Communications
Classifier: Topic :: Software Development :: Libraries
Classifier: Topic :: Software Development :: Libraries :: Python Modules
Classifier: License :: OSI Approved :: BSD License
Classifier: Programming Language :: Python :: 2
Classifier: Programming Language :: Python :: 2.7
Classifier: Programming Language :: Python :: 3
Classifier: Programming Language :: Python :: 3.5
Classifier: Programming Language :: Python :: 3.6
Requires-Dist: pyserial
